MANIFEST.in
README.md
setup.cfg
setup.py
actin/VERSION
actin/__init__.py
actin/__main__.py
actin/actin.py
actin/config_lines.txt
actin.egg-info/PKG-INFO
actin.egg-info/SOURCES.txt
actin.egg-info/dependency_links.txt
actin.egg-info/entry_points.txt
actin.egg-info/requires.txt
actin.egg-info/top_level.txt
actin/__pycache__/__init__.cpython-37.pyc
actin/__pycache__/actin.cpython-37.pyc
actin/actin_files/ac_calc_ind.py
actin/actin_files/ac_config.py
actin/actin_files/ac_get_win.py
actin/actin_files/ac_plot_time.py
actin/actin_files/ac_read_data.py
actin/actin_files/ac_save.py
actin/actin_files/ac_settings.py
actin/actin_files/ac_tools.py
actin/actin_files/__pycache__/ac_calc_ind.cpython-37.pyc
actin/actin_files/__pycache__/ac_config.cpython-37.pyc
actin/actin_files/__pycache__/ac_get_win.cpython-37.pyc
actin/actin_files/__pycache__/ac_plot_time.cpython-37.pyc
actin/actin_files/__pycache__/ac_read_data.cpython-37.pyc
actin/actin_files/__pycache__/ac_save.cpython-37.pyc
actin/actin_files/__pycache__/ac_settings.cpython-37.pyc
actin/actin_files/__pycache__/ac_tools.cpython-37.pyc
actin/test_files/2010-09-18T23:42:36.178_spec.rdb
actin/test_files/ADP.2014-09-16T11:04:45.123.fits
actin/test_files/HARPS.2003-12-12T21:42:45.093_blaze_A.fits
actin/test_files/HARPS.2003-12-12T21:47:59.366_wave_A.fits
actin/test_files/HARPS.2003-12-13T06:19:48.371_bis_M2_A.fits
actin/test_files/HARPS.2003-12-13T06:19:48.371_ccf_M2_A.fits
actin/test_files/HARPS.2003-12-13T06:19:48.371_e2ds_A.fits
actin/test_files/HARPS.2006-07-05T03:52:40.071_bis_G2_A.fits
actin/test_files/HARPS.2006-07-05T03:52:40.071_ccf_G2_A.fits
actin/test_files/HARPS.2010-09-18T23:42:36.178_bis_M2_A.fits
actin/test_files/HARPS.2010-09-18T23:42:36.178_ccf_M2_A.fits
actin/test_files/HARPS.2010-09-18T23:42:36.178_s1d_A.fits
actin/test_files/HD41248_1_1_S1D_A.fits
actin/test_files/HD41248_1_1_S2D_A.fits